synthetic/__init__.py
synthetic/errors.py
synthetic/re.py
synthetic/agents/__init__.py
synthetic/agents/agent_output.py
synthetic/agents/base.py
synthetic/components/__init__.py
synthetic/components/base.py
synthetic/components/funation_call_description.py
synthetic/components/function_description.py
synthetic/components/load_components.py
synthetic/functions/__init__.py
synthetic/functions/base.py
synthetic/functions/decorators.py
synthetic/llms/__init__.py
synthetic/llms/fake.py
synthetic/prompts/__init__.py
synthetic/prompts/base.py
synthetic_cognition-0.2.3.dist-info/LICENSE
synthetic_cognition-0.2.3.dist-info/METADATA
synthetic_cognition-0.2.3.dist-info/WHEEL
synthetic_cognition-0.2.3.dist-info/top_level.txt
synthetic_cognition-0.2.3.dist-info/RECORD
