Metadata-Version: 2.1
Name: synthetic-cognition
Version: 0.2.3
Summary: Synthetic Cognition general inference architecture for language model agents DEMO
Author: Carlos Fernández Lorán
Author-email: carlos.ferlo6165@gmail.com
Keywords: language models,inference,agents,autonomous,llm
License-File: LICENSE
